multicomplex.cpython-39-darwin.so
multicomplex-0.13.0.dist-info/METADATA
multicomplex-0.13.0.dist-info/WHEEL
multicomplex-0.13.0.dist-info/top_level.txt
multicomplex-0.13.0.dist-info/RECORD
