Metadata-Version: 2.1
Name: multicomplex
Version: 0.13.0
Summary: Multicomplex algebra in C++ with wrapper in python
Home-page: UNKNOWN
Author: Ian Bell, Ulrich Deiters, Bradley Alpert
Author-email: ian.bell@nist.gov
License: UNKNOWN
Platform: UNKNOWN
